landregistry/exceptions/__init__.py
landregistry/exceptions/application_error.py
landregistry/exceptions/codes.py
landregistry/exceptions/handlers.py
landregistry/exceptions/py.typed
landregistry_exception_handlers-2.0.1.dist-info/METADATA
landregistry_exception_handlers-2.0.1.dist-info/WHEEL
landregistry_exception_handlers-2.0.1.dist-info/top_level.txt
landregistry_exception_handlers-2.0.1.dist-info/RECORD
