Metadata-Version: 2.1
Name: landregistry-exception-handlers
Version: 2.0.1
Summary: Standardised exception handlers for HMLR Flask applications
Author: Ian Harvey
Author-email: ian.harvey@landregistry.gov.uk
License: MIT
Requires-Python: >=3.9
Requires-Dist: flask >=2.3.0
Requires-Dist: werkzeug >=2.3.0
